nebula2/Config.py
nebula2/Exception.py
nebula2/__init__.py
nebula2/common/__init__.py
nebula2/common/constants.py
nebula2/common/ttypes.py
nebula2/data/DataObject.py
nebula2/data/ResultSet.py
nebula2/data/__init__.py
nebula2/fbthrift/TMultiplexedProcessor.py
nebula2/fbthrift/TSCons.py
nebula2/fbthrift/Thrift.py
nebula2/fbthrift/__init__.py
nebula2/fbthrift/protocol/TBinaryProtocol.py
nebula2/fbthrift/protocol/TCompactProtocol.py
nebula2/fbthrift/protocol/THeaderProtocol.py
nebula2/fbthrift/protocol/TJSONProtocol.py
nebula2/fbthrift/protocol/TMultiplexedProtocol.py
nebula2/fbthrift/protocol/TProtocol.py
nebula2/fbthrift/protocol/TProtocolDecorator.py
nebula2/fbthrift/protocol/TSimpleJSONProtocol.py
nebula2/fbthrift/protocol/__init__.py
nebula2/fbthrift/protocol/exceptions.py
nebula2/fbthrift/server/TAsyncioServer.py
nebula2/fbthrift/server/TCppServer.py
nebula2/fbthrift/server/TServer.py
nebula2/fbthrift/server/__init__.py
nebula2/fbthrift/transport/THeaderTransport.py
nebula2/fbthrift/transport/THttpClient.py
nebula2/fbthrift/transport/TSSLSocket.py
nebula2/fbthrift/transport/TSSLSocketOverHttpTunnel.py
nebula2/fbthrift/transport/TSocket.py
nebula2/fbthrift/transport/TSocketOverHttpTunnel.py
nebula2/fbthrift/transport/TSocketTest.py
nebula2/fbthrift/transport/TTransport.py
nebula2/fbthrift/transport/__init__.py
nebula2/fbthrift/util/BytesStrIO.py
nebula2/fbthrift/util/Decorators.py
nebula2/fbthrift/util/Recursive.py
nebula2/fbthrift/util/Serializer.py
nebula2/fbthrift/util/TCppServerTestManager.py
nebula2/fbthrift/util/TCppServerTestManagerTest.py
nebula2/fbthrift/util/TValidator.py
nebula2/fbthrift/util/__init__.py
nebula2/fbthrift/util/async_common.py
nebula2/fbthrift/util/asyncio.py
nebula2/fbthrift/util/converter.py
nebula2/fbthrift/util/fuzzer.py
nebula2/fbthrift/util/inspect.py
nebula2/fbthrift/util/randomizer.py
nebula2/fbthrift/util/remote.py
nebula2/fbthrift/util/type_inspect.py
nebula2/gclient/__init__.py
nebula2/gclient/net/AuthResult.py
nebula2_python-2.6.1.dist-info/METADATA
nebula2_python-2.6.1.dist-info/WHEEL
nebula2_python-2.6.1.dist-info/top_level.txt
nebula2_python-2.6.1.dist-info/RECORD
