Metadata-Version: 2.1
Name: nebula2-python
Version: 2.6.1
Summary: Python client for Nebula Graph V2.6
Home-page: https://github.com/vesoft-inc/nebula-python
Author: vesoft-inc
Author-email: info@vesoft.com
License: Apache 2.0
Platform: 3.5, 3.7
Requires-Dist: httplib2
Requires-Dist: future
Requires-Dist: six
Requires-Dist: pytz
